llm_openhands.py
llm_openhands-0.0.2.dist-info/licenses/LICENSE
llm_openhands-0.0.2.dist-info/METADATA
llm_openhands-0.0.2.dist-info/WHEEL
llm_openhands-0.0.2.dist-info/entry_points.txt
llm_openhands-0.0.2.dist-info/top_level.txt
llm_openhands-0.0.2.dist-info/RECORD
